hstspreload/__init__.py
hstspreload/hstspreload.bin
hstspreload-2020.11.21.dist-info/LICENSE
hstspreload-2020.11.21.dist-info/METADATA
hstspreload-2020.11.21.dist-info/WHEEL
hstspreload-2020.11.21.dist-info/top_level.txt
hstspreload-2020.11.21.dist-info/RECORD
