Metadata-Version: 2.1
Name: hstspreload
Version: 2020.11.21
Summary: Chromium HSTS Preload list as a Python package
Home-page: https://github.com/sethmlarson/hstspreload
Author: Seth Michael Larson
Author-email: sethmichaellarson@gmail.com
License: BSD-3
Platform: UNKNOWN
Classifier: Development Status :: 5 - Production/Stable
Classifier: Environment :: Web Environment
Classifier: Intended Audience :: Developers
Classifier: License :: OSI Approved :: BSD License
Classifier: Programming Language :: Python :: 3
Classifier: Programming Language :: Python :: 3 :: Only
Classifier: Programming Language :: Python :: 3.6
Classifier: Programming Language :: Python :: 3.7
Classifier: Programming Language :: Python :: 3.8
Classifier: Topic :: Internet :: WWW/HTTP
Classifier: Topic :: Security
Requires-Python: >=3.6
